README.rst
setup.py
deimos/VERSION
deimos/__init__.py
deimos/_struct.py
deimos/argv.py
deimos/cgroups.py
deimos/cleanup.py
deimos/cmd.py
deimos/config.py
deimos/containerizer_pb2.py
deimos/docker.py
deimos/err.py
deimos/flock.py
deimos/logger.py
deimos/mesos.py
deimos/mesos_pb2.py
deimos/path.py
deimos/proto.py
deimos/sig.py
deimos/state.py
deimos/timestamp.py
deimos/usage.py
deimos.egg-info/PKG-INFO
deimos.egg-info/SOURCES.txt
deimos.egg-info/dependency_links.txt
deimos.egg-info/entry_points.txt
deimos.egg-info/requires.txt
deimos.egg-info/top_level.txt
deimos/containerizer/__init__.py
deimos/containerizer/docker.py