Metadata-Version: 1.1
Name: deimos
Version: 0.3.4
Summary: Mesos containerization hooks for Docker
Home-page: https://github.com/mesosphere/deimos
Author: Mesosphere
Author-email: support@mesosphere.io
License: Apache
Platform: UNKNOWN
Classifier: Environment :: Console
Classifier: Intended Audience :: Developers
Classifier: Operating System :: Unix
Classifier: Operating System :: POSIX
Classifier: Programming Language :: Python
Classifier: Topic :: System
Classifier: Topic :: System :: Systems Administration
Classifier: Topic :: Software Development
Classifier: License :: OSI Approved :: Apache Software License
Classifier: Development Status :: 4 - Beta
